{
  "actions": [
    {
      "name": "Разожмёте руки и прыгнете в воду?",
      "next": "208"
    },
    {
      "name": "Не отпуская верёвку, попытаетесь смягчить ногами удар о берег?",
      "next": "196"
    }
  ],
  "text": " Старый мост предательски поскрипывал под ногами у нашего героя. Шаг за шагом Конан продвигался вперёд, прислушиваясь, не рвутся ли изношенные канаты.\n Самые худшие ожидания сбылись, когда варвар был как раз посередине подвесного моста. Канаты звонко лопнули все разом, и дощатый настил перекрутился, как выстиранное бельё в руках у хозяйки. Конан успел лишь вцепиться в верёвочный поручень, и повис над тёмным клокочущим потоком.\n Через несколько мгновений часть моста, оставшаяся у него за спиной, оборвалась окончательно, и Конан вместе с другой половиной полетел, подобно маятнику, в сторону чёрных скал, к противоположному берегу подземной реки."
}