{
  "actions": [
    {
      "name": "Возьмёте ценные находки с собой?",
      "flags": [
        {
          "type": "add_flag",
          "names": [
            "1"
          ]
        }
      ],
      "next": "162"
    },
    {
      "name": "Оставите эти совершенно бесполезные вещи на месте и двинетесь дальше?",
      "next": "156"
    }
  ],
  "text": " Киммериец осторожно просунул руку в узкую отдушину. А вдруг это ловушка? Но тут его рука нащупала какой-то предмет. Это был масляный светильник. Подле него лежали кремень и кресало."
}