{
  "actions": [
    {
      "name": "Начните игру сначала.",
      "flags": [],
      "next": "0"
    }
  ],
  "text": " Конан уклонился от удара копья и сам попытался проткнуть стражника мечом. Но ему попался опытный противник. Стражник отразил удар краем древка и громко крикнул:\n– На помощь! Тревога!\n Из ближайшей двери выскочили ещё несколько вооружённых людей. Киммериец был очень опасным бойцом, однако в таком узком помещении короткие копья стражи оказались значительно эффективнее его меча. Раненный, упав на колени, однако ещё продолжал сопротивляться, но – бесполезно. Не прошло и десяти минут, как довольные стражники отрезали голову варвара и унесли её, чтобы продемонстрировать своему начальству."
}